most_active_cookie/__init__.py
most_active_cookie/__main__.py
most_active_cookie/active_cookie_extractor.py
most_active_cookie/utils.py
most_active_cookie-1.0.0.dist-info/LICENSE
most_active_cookie-1.0.0.dist-info/METADATA
most_active_cookie-1.0.0.dist-info/WHEEL
most_active_cookie-1.0.0.dist-info/top_level.txt
most_active_cookie-1.0.0.dist-info/RECORD
