Metadata-Version: 2.1
Name: most-active-cookie
Version: 1.0.0
Summary: Tools for extracting most active cookie from csv
Home-page: https://github.com/yongchand/MostActiveCookie
Author: Chan Hong
Author-email: hello@chanhong.xyz
Project-URL: Bug Reports, https://github.com/yongchand/MostActiveCookie/issues
Project-URL: Source, https://github.com/yongchand/MostActiveCookie
Classifier: Programming Language :: Python :: 3
Classifier: License :: OSI Approved :: MIT License
Requires-Python: >=3.8,<4
License-File: LICENSE
